LICENSE.txt
MANIFEST.in
README.md
VERSION
setup.cfg
setup.py
./test/__init__.py
./test/test_ude_gym_bridge_import.py
./test/test_ude_gym_bridge/__init__.py
./test/test_ude_gym_bridge/test_gym_environment_adapter.py
./ude_gym_bridge/__init__.py
./ude_gym_bridge/gym_env_remote_runner.py
./ude_gym_bridge/gym_environment_adapter.py
test/test_ude_gym_bridge_import.py
ude_gym_bridge.egg-info/PKG-INFO
ude_gym_bridge.egg-info/SOURCES.txt
ude_gym_bridge.egg-info/dependency_links.txt
ude_gym_bridge.egg-info/requires.txt
ude_gym_bridge.egg-info/top_level.txt