Metadata-Version: 2.1
Name: ude-gym-bridge
Version: 0.1.4
Summary: Open source library to bridge UDE and OpenAI Gym.
Home-page: https://github.com/aws-deepracer/ude-gym-bridge/
Author: Amazon Web Services
License: Apache License 2.0
Keywords: ML RL Amazon AWS AI UDE
Platform: UNKNOWN
Classifier: Development Status :: 4 - Beta
Classifier: Intended Audience :: Developers
Classifier: Natural Language :: English
Classifier: License :: OSI Approved :: Apache Software License
Classifier: Programming Language :: Python
Classifier: Programming Language :: Python :: 3.6
Classifier: Programming Language :: Python :: 3.7
Classifier: Programming Language :: Python :: 3.8
Classifier: Programming Language :: Python :: 3.9
License-File: LICENSE.txt
